__init__.py
base.py
benchmark.py
interrogate.py
veta.py
config/__init__.py
config/tools_config.txt
config/example_imgs/.gitkeep
config/example_imgs/benchmark_af.png
config/example_imgs/benchmark_dist.png
config/example_imgs/benchmark_performance.png
config/example_imgs/benchmark_thresholds.png
config/example_imgs/heatmap.png
config/example_imgs/inspect_ratios.png
config/example_imgs/inspect_ratios2.png
config/example_imgs/logo.png
config/example_imgs/ml_fi.png
config/example_imgs/ml_performance.png
config/example_imgs/pearson_corr.png
config/example_imgs/per_bin_score.png
config/example_imgs/per_bin_score_split_ss.png
config/example_imgs/roc_analysis.png
config/example_imgs/roc_curves.png
plots/__init__.py
plots/plots_benchmark_mode.py
plots/plots_interrogate_mode.py
plots/plots_intronic_analysis.py
plots/plots_machine_learning.py
plots/plots_threshold_analysis.py
plots/plots_utils.py
predictions/__init__.py
predictions/apply.py
predictions/filters.py
predictions/introns.py
predictions/metapredictions.py
predictions/metrics.py
predictions/thresholds.py
predictions/utils_classifiers.py
preprocessing/__init__.py
preprocessing/clinvar.py
preprocessing/location.py
preprocessing/osutils.py
preprocessing/tables.py
preprocessing/utils_tools.py
preprocessing/vcf.py
veta-0.7.7.dist-info/LICENSE
veta-0.7.7.dist-info/METADATA
veta-0.7.7.dist-info/WHEEL
veta-0.7.7.dist-info/entry_points.txt
veta-0.7.7.dist-info/top_level.txt
veta-0.7.7.dist-info/RECORD
