Metadata-Version: 2.1
Name: veta
Version: 0.7.7
Summary: Simple variant prediction evaluation
Author-email: Pedro Barbosa <psbpedrobarbosa@gmail.com>
License: https://opensource.org/licenses/GPL-3.0
Project-URL: homepage, https://github.com/PedroBarbosa/VETA
Project-URL: repository, https://github.com/PedroBarbosa/VETA
Project-URL: documentation, https://github.com/PedroBarbosa/VETA
Requires-Python: ~=3.8
License-File: LICENSE
Requires-Dist: matplotlib (==3.5.1)
Requires-Dist: numpy (==1.23.5)
Requires-Dist: pandas (==1.4.2)
Requires-Dist: seaborn (==0.11.2)
Requires-Dist: cyvcf2 (==0.30.15)
Requires-Dist: scikit-learn (==1.0.2)
Requires-Dist: imbalanced-learn (==0.9.0)
Requires-Dist: hgvs (==1.5.2)
Requires-Dist: fastcluster (==1.2.6)
Requires-Dist: statannotations (==0.4.4)
Requires-Dist: gplearn (==0.4.1)
Requires-Dist: sklearn-pandas (==2.2.0)
Requires-Dist: dtreeviz (==1.3.5)
